[
  {
    "id": "ex001",
    "title": "Barbell back squat",
    "cat": "lower",
    "tags": "legs quads hamstrings glutes calves squat hinge lunge barbell back squat",
    "tip": "Prioritize control, full range where safe, and breathe with the pattern.",
    "thumbUrl": "https://i.ytimg.com/vi/gcNh17Ckjgg/hqdefault.jpg",
    "videoLabel": "YouTube (privacy-enhanced embed)",
    "youtubeId": "gcNh17Ckjgg"
  },
  {
    "id": "ex002",
    "title": "Front squat",
    "cat": "lower",
    "tags": "legs quads hamstrings glutes calves squat hinge lunge front squat",
    "tip": "Prioritize control, full range where safe, and breathe with the pattern.",
    "thumbUrl": "https://i.ytimg.com/vi/qmkjkGmB3v4/hqdefault.jpg",
    "videoLabel": "YouTube (privacy-enhanced embed)",
    "youtubeId": "qmkjkGmB3v4"
  },
  {
    "id": "ex003",
    "title": "Goblet squat",
    "cat": "lower",
    "tags": "legs quads hamstrings glutes calves squat hinge lunge goblet squat",
    "tip": "Prioritize control, full range where safe, and breathe with the pattern.",
    "thumbUrl": "https://i.ytimg.com/vi/Me9i5Old7oQ/hqdefault.jpg",
    "videoLabel": "YouTube (privacy-enhanced embed)",
    "youtubeId": "Me9i5Old7oQ"
  },
  {
    "id": "ex004",
    "title": "Box squat",
    "cat": "lower",
    "tags": "legs quads hamstrings glutes calves squat hinge lunge box squat",
    "tip": "Prioritize control, full range where safe, and breathe with the pattern.",
    "thumbUrl": "https://i.ytimg.com/vi/qyOelMdM4og/hqdefault.jpg",
    "videoLabel": "YouTube (privacy-enhanced embed)",
    "youtubeId": "qyOelMdM4og"
  },
  {
    "id": "ex005",
    "title": "Pause squat",
    "cat": "lower",
    "tags": "legs quads hamstrings glutes calves squat hinge lunge pause squat",
    "tip": "Prioritize control, full range where safe, and breathe with the pattern.",
    "thumbUrl": "https://i.ytimg.com/vi/gcNh17Ckjgg/hqdefault.jpg",
    "videoLabel": "YouTube (privacy-enhanced embed)",
    "youtubeId": "gcNh17Ckjgg"
  },
  {
    "id": "ex006",
    "title": "Overhead squat",
    "cat": "lower",
    "tags": "legs quads hamstrings glutes calves squat hinge lunge overhead squat",
    "tip": "Prioritize control, full range where safe, and breathe with the pattern.",
    "thumbUrl": "https://i.ytimg.com/vi/qSOQhZy0zH8/hqdefault.jpg",
    "videoLabel": "YouTube (privacy-enhanced embed)",
    "youtubeId": "qSOQhZy0zH8"
  },
  {
    "id": "ex007",
    "title": "Zercher squat",
    "cat": "lower",
    "tags": "legs quads hamstrings glutes calves squat hinge lunge zercher squat",
    "tip": "Prioritize control, full range where safe, and breathe with the pattern.",
    "thumbUrl": "https://i.ytimg.com/vi/OZruu0MuF7A/hqdefault.jpg",
    "videoLabel": "YouTube (privacy-enhanced embed)",
    "youtubeId": "OZruu0MuF7A"
  },
  {
    "id": "ex008",
    "title": "Hack squat machine",
    "cat": "lower",
    "tags": "legs quads hamstrings glutes calves squat hinge lunge hack squat machine",
    "tip": "Prioritize control, full range where safe, and breathe with the pattern.",
    "thumbUrl": "https://i.ytimg.com/vi/3wNd9Vg6g4A/hqdefault.jpg",
    "videoLabel": "YouTube (privacy-enhanced embed)",
    "youtubeId": "3wNd9Vg6g4A"
  },
  {
    "id": "ex009",
    "title": "Leg press 45",
    "cat": "lower",
    "tags": "legs quads hamstrings glutes calves squat hinge lunge leg press 45",
    "tip": "Prioritize control, full range where safe, and breathe with the pattern.",
    "thumbUrl": "https://i.ytimg.com/vi/3wNd9Vg6g4A/hqdefault.jpg",
    "videoLabel": "YouTube (privacy-enhanced embed)",
    "youtubeId": "3wNd9Vg6g4A"
  },
  {
    "id": "ex010",
    "title": "Leg press narrow",
    "cat": "lower",
    "tags": "legs quads hamstrings glutes calves squat hinge lunge leg press narrow",
    "tip": "Prioritize control, full range where safe, and breathe with the pattern.",
    "thumbUrl": "https://i.ytimg.com/vi/3wNd9Vg6g4A/hqdefault.jpg",
    "videoLabel": "YouTube (privacy-enhanced embed)",
    "youtubeId": "3wNd9Vg6g4A"
  },
  {
    "id": "ex011",
    "title": "Leg extension",
    "cat": "lower",
    "tags": "legs quads hamstrings glutes calves squat hinge lunge leg extension",
    "tip": "Prioritize control, full range where safe, and breathe with the pattern.",
    "thumbUrl": "https://i.ytimg.com/vi/T8vLb1YU2Ps/hqdefault.jpg",
    "videoLabel": "YouTube (privacy-enhanced embed)",
    "youtubeId": "T8vLb1YU2Ps"
  },
  {
    "id": "ex012",
    "title": "Sissy squat",
    "cat": "lower",
    "tags": "legs quads hamstrings glutes calves squat hinge lunge sissy squat",
    "tip": "Prioritize control, full range where safe, and breathe with the pattern.",
    "thumbUrl": "https://i.ytimg.com/vi/gcNh17Ckjgg/hqdefault.jpg",
    "videoLabel": "YouTube (privacy-enhanced embed)",
    "youtubeId": "gcNh17Ckjgg"
  },
  {
    "id": "ex013",
    "title": "Walking lunge",
    "cat": "lower",
    "tags": "legs quads hamstrings glutes calves squat hinge lunge walking lunge",
    "tip": "Prioritize control, full range where safe, and breathe with the pattern.",
    "thumbUrl": "https://i.ytimg.com/vi/QFZ4q2jDUyY/hqdefault.jpg",
    "videoLabel": "YouTube (privacy-enhanced embed)",
    "youtubeId": "QFZ4q2jDUyY"
  },
  {
    "id": "ex014",
    "title": "Reverse lunge",
    "cat": "lower",
    "tags": "legs quads hamstrings glutes calves squat hinge lunge reverse lunge",
    "tip": "Prioritize control, full range where safe, and breathe with the pattern.",
    "thumbUrl": "https://i.ytimg.com/vi/QFZ4q2jDUyY/hqdefault.jpg",
    "videoLabel": "YouTube (privacy-enhanced embed)",
    "youtubeId": "QFZ4q2jDUyY"
  },
  {
    "id": "ex015",
    "title": "Curtsy lunge",
    "cat": "lower",
    "tags": "legs quads hamstrings glutes calves squat hinge lunge curtsy lunge",
    "tip": "Prioritize control, full range where safe, and breathe with the pattern.",
    "thumbUrl": "https://i.ytimg.com/vi/QFZ4q2jDUyY/hqdefault.jpg",
    "videoLabel": "YouTube (privacy-enhanced embed)",
    "youtubeId": "QFZ4q2jDUyY"
  },
  {
    "id": "ex016",
    "title": "Bulgarian split squat",
    "cat": "lower",
    "tags": "legs quads hamstrings glutes calves squat hinge lunge bulgarian split squat",
    "tip": "Prioritize control, full range where safe, and breathe with the pattern.",
    "thumbUrl": "https://i.ytimg.com/vi/2K2Wm7Z8Yc/hqdefault.jpg",
    "videoLabel": "YouTube (privacy-enhanced embed)",
    "youtubeId": "2K2Wm7Z8Yc"
  },
  {
    "id": "ex017",
    "title": "Step-up",
    "cat": "lower",
    "tags": "legs quads hamstrings glutes calves squat hinge lunge step-up",
    "tip": "Prioritize control, full range where safe, and breathe with the pattern.",
    "thumbUrl": "https://i.ytimg.com/vi/QFZ4q2jDUyY/hqdefault.jpg",
    "videoLabel": "YouTube (privacy-enhanced embed)",
    "youtubeId": "QFZ4q2jDUyY"
  },
  {
    "id": "ex018",
    "title": "Cossack squat",
    "cat": "lower",
    "tags": "legs quads hamstrings glutes calves squat hinge lunge cossack squat",
    "tip": "Prioritize control, full range where safe, and breathe with the pattern.",
    "thumbUrl": "https://i.ytimg.com/vi/gcNh17Ckjgg/hqdefault.jpg",
    "videoLabel": "YouTube (privacy-enhanced embed)",
    "youtubeId": "gcNh17Ckjgg"
  },
  {
    "id": "ex019",
    "title": "Wall sit",
    "cat": "lower",
    "tags": "legs quads hamstrings glutes calves squat hinge lunge wall sit",
    "tip": "Prioritize control, full range where safe, and breathe with the pattern.",
    "thumbUrl": "https://i.ytimg.com/vi/gcNh17Ckjgg/hqdefault.jpg",
    "videoLabel": "YouTube (privacy-enhanced embed)",
    "youtubeId": "gcNh17Ckjgg"
  },
  {
    "id": "ex020",
    "title": "Conventional deadlift",
    "cat": "lower",
    "tags": "legs quads hamstrings glutes calves squat hinge lunge conventional deadlift",
    "tip": "Prioritize control, full range where safe, and breathe with the pattern.",
    "thumbUrl": "https://i.ytimg.com/vi/ZaTM37cfiDs/hqdefault.jpg",
    "videoLabel": "YouTube (privacy-enhanced embed)",
    "youtubeId": "ZaTM37cfiDs"
  },
  {
    "id": "ex021",
    "title": "Sumo deadlift",
    "cat": "lower",
    "tags": "legs quads hamstrings glutes calves squat hinge lunge sumo deadlift",
    "tip": "Prioritize control, full range where safe, and breathe with the pattern.",
    "thumbUrl": "https://i.ytimg.com/vi/ZaTM37cfiDs/hqdefault.jpg",
    "videoLabel": "YouTube (privacy-enhanced embed)",
    "youtubeId": "ZaTM37cfiDs"
  },
  {
    "id": "ex022",
    "title": "Romanian deadlift",
    "cat": "lower",
    "tags": "legs quads hamstrings glutes calves squat hinge lunge romanian deadlift",
    "tip": "Prioritize control, full range where safe, and breathe with the pattern.",
    "thumbUrl": "https://i.ytimg.com/vi/jEy_czb3RKA/hqdefault.jpg",
    "videoLabel": "YouTube (privacy-enhanced embed)",
    "youtubeId": "jEy_czb3RKA"
  },
  {
    "id": "ex023",
    "title": "Stiff-leg deadlift",
    "cat": "lower",
    "tags": "legs quads hamstrings glutes calves squat hinge lunge stiff-leg deadlift",
    "tip": "Prioritize control, full range where safe, and breathe with the pattern.",
    "thumbUrl": "https://i.ytimg.com/vi/jEy_czb3RKA/hqdefault.jpg",
    "videoLabel": "YouTube (privacy-enhanced embed)",
    "youtubeId": "jEy_czb3RKA"
  },
  {
    "id": "ex024",
    "title": "Trap bar deadlift",
    "cat": "lower",
    "tags": "legs quads hamstrings glutes calves squat hinge lunge trap bar deadlift",
    "tip": "Prioritize control, full range where safe, and breathe with the pattern.",
    "thumbUrl": "https://i.ytimg.com/vi/ZaTM37cfiDs/hqdefault.jpg",
    "videoLabel": "YouTube (privacy-enhanced embed)",
    "youtubeId": "ZaTM37cfiDs"
  },
  {
    "id": "ex025",
    "title": "Rack pull",
    "cat": "lower",
    "tags": "legs quads hamstrings glutes calves squat hinge lunge rack pull",
    "tip": "Prioritize control, full range where safe, and breathe with the pattern.",
    "thumbUrl": "https://i.ytimg.com/vi/ZaTM37cfiDs/hqdefault.jpg",
    "videoLabel": "YouTube (privacy-enhanced embed)",
    "youtubeId": "ZaTM37cfiDs"
  },
  {
    "id": "ex026",
    "title": "Good morning",
    "cat": "lower",
    "tags": "legs quads hamstrings glutes calves squat hinge lunge good morning",
    "tip": "Prioritize control, full range where safe, and breathe with the pattern.",
    "thumbUrl": "https://i.ytimg.com/vi/ytGaGWC_3WQ/hqdefault.jpg",
    "videoLabel": "YouTube (privacy-enhanced embed)",
    "youtubeId": "ytGaGWC_3WQ"
  },
  {
    "id": "ex027",
    "title": "Barbell hip thrust",
    "cat": "lower",
    "tags": "legs quads hamstrings glutes calves squat hinge lunge barbell hip thrust",
    "tip": "Prioritize control, full range where safe, and breathe with the pattern.",
    "thumbUrl": "https://i.ytimg.com/vi/xDmFk_JWGfg/hqdefault.jpg",
    "videoLabel": "YouTube (privacy-enhanced embed)",
    "youtubeId": "xDmFk_JWGfg"
  },
  {
    "id": "ex028",
    "title": "Glute bridge",
    "cat": "lower",
    "tags": "legs quads hamstrings glutes calves squat hinge lunge glute bridge",
    "tip": "Prioritize control, full range where safe, and breathe with the pattern.",
    "thumbUrl": "https://i.ytimg.com/vi/xDmFk_JWGfg/hqdefault.jpg",
    "videoLabel": "YouTube (privacy-enhanced embed)",
    "youtubeId": "xDmFk_JWGfg"
  },
  {
    "id": "ex029",
    "title": "Single-leg RDL",
    "cat": "lower",
    "tags": "legs quads hamstrings glutes calves squat hinge lunge single-leg rdl",
    "tip": "Prioritize control, full range where safe, and breathe with the pattern.",
    "thumbUrl": "https://i.ytimg.com/vi/jEy_czb3RKA/hqdefault.jpg",
    "videoLabel": "YouTube (privacy-enhanced embed)",
    "youtubeId": "jEy_czb3RKA"
  },
  {
    "id": "ex030",
    "title": "Cable pull-through",
    "cat": "lower",
    "tags": "legs quads hamstrings glutes calves squat hinge lunge cable pull-through",
    "tip": "Prioritize control, full range where safe, and breathe with the pattern.",
    "thumbUrl": "https://i.ytimg.com/vi/L2g0jxZFXow/hqdefault.jpg",
    "videoLabel": "YouTube (privacy-enhanced embed)",
    "youtubeId": "L2g0jxZFXow"
  },
  {
    "id": "ex031",
    "title": "Nordic ham curl",
    "cat": "lower",
    "tags": "legs quads hamstrings glutes calves squat hinge lunge nordic ham curl",
    "tip": "Prioritize control, full range where safe, and breathe with the pattern.",
    "thumbUrl": "https://i.ytimg.com/vi/NBY9-kTuohk/hqdefault.jpg",
    "videoLabel": "YouTube (privacy-enhanced embed)",
    "youtubeId": "NBY9-kTuohk"
  },
  {
    "id": "ex032",
    "title": "Seated leg curl",
    "cat": "lower",
    "tags": "legs quads hamstrings glutes calves squat hinge lunge seated leg curl",
    "tip": "Prioritize control, full range where safe, and breathe with the pattern.",
    "thumbUrl": "https://i.ytimg.com/vi/pI65w6ebY9g/hqdefault.jpg",
    "videoLabel": "YouTube (privacy-enhanced embed)",
    "youtubeId": "pI65w6ebY9g"
  },
  {
    "id": "ex033",
    "title": "Lying leg curl",
    "cat": "lower",
    "tags": "legs quads hamstrings glutes calves squat hinge lunge lying leg curl",
    "tip": "Prioritize control, full range where safe, and breathe with the pattern.",
    "thumbUrl": "https://i.ytimg.com/vi/pI65w6ebY9g/hqdefault.jpg",
    "videoLabel": "YouTube (privacy-enhanced embed)",
    "youtubeId": "pI65w6ebY9g"
  },
  {
    "id": "ex034",
    "title": "Standing calf raise",
    "cat": "lower",
    "tags": "legs quads hamstrings glutes calves squat hinge lunge standing calf raise",
    "tip": "Prioritize control, full range where safe, and breathe with the pattern.",
    "thumbUrl": "https://i.ytimg.com/vi/gwLzBJYoWlI/hqdefault.jpg",
    "videoLabel": "YouTube (privacy-enhanced embed)",
    "youtubeId": "gwLzBJYoWlI"
  },
  {
    "id": "ex035",
    "title": "Seated calf raise",
    "cat": "lower",
    "tags": "legs quads hamstrings glutes calves squat hinge lunge seated calf raise",
    "tip": "Prioritize control, full range where safe, and breathe with the pattern.",
    "thumbUrl": "https://i.ytimg.com/vi/gwLzBJYoWlI/hqdefault.jpg",
    "videoLabel": "YouTube (privacy-enhanced embed)",
    "youtubeId": "gwLzBJYoWlI"
  },
  {
    "id": "ex036",
    "title": "Donkey calf raise",
    "cat": "lower",
    "tags": "legs quads hamstrings glutes calves squat hinge lunge donkey calf raise",
    "tip": "Prioritize control, full range where safe, and breathe with the pattern.",
    "thumbUrl": "https://i.ytimg.com/vi/gwLzBJYoWlI/hqdefault.jpg",
    "videoLabel": "YouTube (privacy-enhanced embed)",
    "youtubeId": "gwLzBJYoWlI"
  },
  {
    "id": "ex037",
    "title": "Tibialis raise",
    "cat": "lower",
    "tags": "legs quads hamstrings glutes calves squat hinge lunge tibialis raise",
    "tip": "Prioritize control, full range where safe, and breathe with the pattern.",
    "thumbUrl": "https://i.ytimg.com/vi/gwLzBJYoWlI/hqdefault.jpg",
    "videoLabel": "YouTube (privacy-enhanced embed)",
    "youtubeId": "gwLzBJYoWlI"
  },
  {
    "id": "ex038",
    "title": "Farmer carry",
    "cat": "lower",
    "tags": "legs quads hamstrings glutes calves squat hinge lunge farmer carry",
    "tip": "Prioritize control, full range where safe, and breathe with the pattern.",
    "thumbUrl": "https://i.ytimg.com/vi/tpqdbnCjzZ4/hqdefault.jpg",
    "videoLabel": "YouTube (privacy-enhanced embed)",
    "youtubeId": "tpqdbnCjzZ4"
  },
  {
    "id": "ex039",
    "title": "Suitcase carry",
    "cat": "lower",
    "tags": "legs quads hamstrings glutes calves squat hinge lunge suitcase carry",
    "tip": "Prioritize control, full range where safe, and breathe with the pattern.",
    "thumbUrl": "https://i.ytimg.com/vi/tpqdbnCjzZ4/hqdefault.jpg",
    "videoLabel": "YouTube (privacy-enhanced embed)",
    "youtubeId": "tpqdbnCjzZ4"
  },
  {
    "id": "ex040",
    "title": "Overhead carry",
    "cat": "lower",
    "tags": "legs quads hamstrings glutes calves squat hinge lunge overhead carry",
    "tip": "Prioritize control, full range where safe, and breathe with the pattern.",
    "thumbUrl": "https://i.ytimg.com/vi/tpqdbnCjzZ4/hqdefault.jpg",
    "videoLabel": "YouTube (privacy-enhanced embed)",
    "youtubeId": "tpqdbnCjzZ4"
  },
  {
    "id": "ex041",
    "title": "Barbell bench press",
    "cat": "upper_push",
    "tags": "chest shoulders triceps push pressing barbell bench press",
    "tip": "Prioritize control, full range where safe, and breathe with the pattern.",
    "thumbUrl": "https://i.ytimg.com/vi/vcBig73ojpE/hqdefault.jpg",
    "videoLabel": "YouTube (privacy-enhanced embed)",
    "youtubeId": "vcBig73ojpE"
  },
  {
    "id": "ex042",
    "title": "Close-grip bench",
    "cat": "upper_push",
    "tags": "chest shoulders triceps push pressing close-grip bench",
    "tip": "Prioritize control, full range where safe, and breathe with the pattern.",
    "thumbUrl": "https://i.ytimg.com/vi/vcBig73ojpE/hqdefault.jpg",
    "videoLabel": "YouTube (privacy-enhanced embed)",
    "youtubeId": "vcBig73ojpE"
  },
  {
    "id": "ex043",
    "title": "Incline barbell bench",
    "cat": "upper_push",
    "tags": "chest shoulders triceps push pressing incline barbell bench",
    "tip": "Prioritize control, full range where safe, and breathe with the pattern.",
    "thumbUrl": "https://i.ytimg.com/vi/YaXPRqUwItQ/hqdefault.jpg",
    "videoLabel": "YouTube (privacy-enhanced embed)",
    "youtubeId": "YaXPRqUwItQ"
  },
  {
    "id": "ex044",
    "title": "Decline bench press",
    "cat": "upper_push",
    "tags": "chest shoulders triceps push pressing decline bench press",
    "tip": "Prioritize control, full range where safe, and breathe with the pattern.",
    "thumbUrl": "https://i.ytimg.com/vi/vcBig73ojpE/hqdefault.jpg",
    "videoLabel": "YouTube (privacy-enhanced embed)",
    "youtubeId": "vcBig73ojpE"
  },
  {
    "id": "ex045",
    "title": "Dumbbell bench press",
    "cat": "upper_push",
    "tags": "chest shoulders triceps push pressing dumbbell bench press",
    "tip": "Prioritize control, full range where safe, and breathe with the pattern.",
    "thumbUrl": "https://i.ytimg.com/vi/vcBig73ojpE/hqdefault.jpg",
    "videoLabel": "YouTube (privacy-enhanced embed)",
    "youtubeId": "vcBig73ojpE"
  },
  {
    "id": "ex046",
    "title": "Incline dumbbell press",
    "cat": "upper_push",
    "tags": "chest shoulders triceps push pressing incline dumbbell press",
    "tip": "Prioritize control, full range where safe, and breathe with the pattern.",
    "thumbUrl": "https://i.ytimg.com/vi/YaXPRqUwItQ/hqdefault.jpg",
    "videoLabel": "YouTube (privacy-enhanced embed)",
    "youtubeId": "YaXPRqUwItQ"
  },
  {
    "id": "ex047",
    "title": "Arnold press",
    "cat": "upper_push",
    "tags": "chest shoulders triceps push pressing arnold press",
    "tip": "Prioritize control, full range where safe, and breathe with the pattern.",
    "thumbUrl": "https://i.ytimg.com/vi/gvmhug-SdBY/hqdefault.jpg",
    "videoLabel": "YouTube (privacy-enhanced embed)",
    "youtubeId": "gvmhug-SdBY"
  },
  {
    "id": "ex048",
    "title": "Dumbbell shoulder press",
    "cat": "upper_push",
    "tags": "chest shoulders triceps push pressing dumbbell shoulder press",
    "tip": "Prioritize control, full range where safe, and breathe with the pattern.",
    "thumbUrl": "https://i.ytimg.com/vi/g3du8q1Yn8k/hqdefault.jpg",
    "videoLabel": "YouTube (privacy-enhanced embed)",
    "youtubeId": "g3du8q1Yn8k"
  },
  {
    "id": "ex049",
    "title": "Machine chest press",
    "cat": "upper_push",
    "tags": "chest shoulders triceps push pressing machine chest press",
    "tip": "Prioritize control, full range where safe, and breathe with the pattern.",
    "thumbUrl": "https://i.ytimg.com/vi/vcBig73ojpE/hqdefault.jpg",
    "videoLabel": "YouTube (privacy-enhanced embed)",
    "youtubeId": "vcBig73ojpE"
  },
  {
    "id": "ex050",
    "title": "Cable crossover",
    "cat": "upper_push",
    "tags": "chest shoulders triceps push pressing cable crossover",
    "tip": "Prioritize control, full range where safe, and breathe with the pattern.",
    "thumbUrl": "https://i.ytimg.com/vi/IODxDxX7oi4/hqdefault.jpg",
    "videoLabel": "YouTube (privacy-enhanced embed)",
    "youtubeId": "IODxDxX7oi4"
  },
  {
    "id": "ex051",
    "title": "Incline cable fly",
    "cat": "upper_push",
    "tags": "chest shoulders triceps push pressing incline cable fly",
    "tip": "Prioritize control, full range where safe, and breathe with the pattern.",
    "thumbUrl": "https://i.ytimg.com/vi/IODxDxX7oi4/hqdefault.jpg",
    "videoLabel": "YouTube (privacy-enhanced embed)",
    "youtubeId": "IODxDxX7oi4"
  },
  {
    "id": "ex052",
    "title": "Pec deck fly",
    "cat": "upper_push",
    "tags": "chest shoulders triceps push pressing pec deck fly",
    "tip": "Prioritize control, full range where safe, and breathe with the pattern.",
    "thumbUrl": "https://i.ytimg.com/vi/IODxDxX7oi4/hqdefault.jpg",
    "videoLabel": "YouTube (privacy-enhanced embed)",
    "youtubeId": "IODxDxX7oi4"
  },
  {
    "id": "ex053",
    "title": "Push-up",
    "cat": "calisthenics",
    "tags": "bodyweight pullups dips pushups rings push-up",
    "tip": "Prioritize control, full range where safe, and breathe with the pattern.",
    "thumbUrl": "https://i.ytimg.com/vi/Ahdu_UdZul4/hqdefault.jpg",
    "videoLabel": "YouTube (privacy-enhanced embed)",
    "youtubeId": "Ahdu_UdZul4"
  },
  {
    "id": "ex054",
    "title": "Diamond push-up",
    "cat": "calisthenics",
    "tags": "bodyweight pullups dips pushups rings diamond push-up",
    "tip": "Prioritize control, full range where safe, and breathe with the pattern.",
    "thumbUrl": "https://i.ytimg.com/vi/Ahdu_UdZul4/hqdefault.jpg",
    "videoLabel": "YouTube (privacy-enhanced embed)",
    "youtubeId": "Ahdu_UdZul4"
  },
  {
    "id": "ex055",
    "title": "Wide push-up",
    "cat": "calisthenics",
    "tags": "bodyweight pullups dips pushups rings wide push-up",
    "tip": "Prioritize control, full range where safe, and breathe with the pattern.",
    "thumbUrl": "https://i.ytimg.com/vi/Ahdu_UdZul4/hqdefault.jpg",
    "videoLabel": "YouTube (privacy-enhanced embed)",
    "youtubeId": "Ahdu_UdZul4"
  },
  {
    "id": "ex056",
    "title": "Archer push-up",
    "cat": "calisthenics",
    "tags": "bodyweight pullups dips pushups rings archer push-up",
    "tip": "Prioritize control, full range where safe, and breathe with the pattern.",
    "thumbUrl": "https://i.ytimg.com/vi/Ahdu_UdZul4/hqdefault.jpg",
    "videoLabel": "YouTube (privacy-enhanced embed)",
    "youtubeId": "Ahdu_UdZul4"
  },
  {
    "id": "ex057",
    "title": "Ring dip",
    "cat": "calisthenics",
    "tags": "bodyweight pullups dips pushups rings ring dip",
    "tip": "Prioritize control, full range where safe, and breathe with the pattern.",
    "thumbUrl": "https://i.ytimg.com/vi/yN6Q1QWdNnA/hqdefault.jpg",
    "videoLabel": "YouTube (privacy-enhanced embed)",
    "youtubeId": "yN6Q1QWdNnA"
  },
  {
    "id": "ex058",
    "title": "Parallel bar dip",
    "cat": "calisthenics",
    "tags": "bodyweight pullups dips pushups rings parallel bar dip",
    "tip": "Prioritize control, full range where safe, and breathe with the pattern.",
    "thumbUrl": "https://i.ytimg.com/vi/yN6Q1QWdNnA/hqdefault.jpg",
    "videoLabel": "YouTube (privacy-enhanced embed)",
    "youtubeId": "yN6Q1QWdNnA"
  },
  {
    "id": "ex059",
    "title": "Chest dip",
    "cat": "upper_push",
    "tags": "chest shoulders triceps push pressing chest dip",
    "tip": "Prioritize control, full range where safe, and breathe with the pattern.",
    "thumbUrl": "https://i.ytimg.com/vi/yN6Q1QWdNnA/hqdefault.jpg",
    "videoLabel": "YouTube (privacy-enhanced embed)",
    "youtubeId": "yN6Q1QWdNnA"
  },
  {
    "id": "ex060",
    "title": "Pull-up",
    "cat": "calisthenics",
    "tags": "bodyweight pullups dips pushups rings pull-up",
    "tip": "Prioritize control, full range where safe, and breathe with the pattern.",
    "thumbUrl": "https://i.ytimg.com/vi/eDP_CH--eJc/hqdefault.jpg",
    "videoLabel": "YouTube (privacy-enhanced embed)",
    "youtubeId": "eDP_CH--eJc"
  },
  {
    "id": "ex061",
    "title": "Chin-up",
    "cat": "calisthenics",
    "tags": "bodyweight pullups dips pushups rings chin-up",
    "tip": "Prioritize control, full range where safe, and breathe with the pattern.",
    "thumbUrl": "https://i.ytimg.com/vi/brhRxr6FhAs/hqdefault.jpg",
    "videoLabel": "YouTube (privacy-enhanced embed)",
    "youtubeId": "brhRxr6FhAs"
  },
  {
    "id": "ex062",
    "title": "Neutral-grip pull-up",
    "cat": "calisthenics",
    "tags": "bodyweight pullups dips pushups rings neutral-grip pull-up",
    "tip": "Prioritize control, full range where safe, and breathe with the pattern.",
    "thumbUrl": "https://i.ytimg.com/vi/eDP_CH--eJc/hqdefault.jpg",
    "videoLabel": "YouTube (privacy-enhanced embed)",
    "youtubeId": "eDP_CH--eJc"
  },
  {
    "id": "ex063",
    "title": "Lat pulldown",
    "cat": "upper_pull",
    "tags": "back biceps lats traps pulling rowing lat pulldown",
    "tip": "Prioritize control, full range where safe, and breathe with the pattern.",
    "thumbUrl": "https://i.ytimg.com/vi/sY9T_dHDxNM/hqdefault.jpg",
    "videoLabel": "YouTube (privacy-enhanced embed)",
    "youtubeId": "sY9T_dHDxNM"
  },
  {
    "id": "ex064",
    "title": "Straight-arm pulldown",
    "cat": "upper_pull",
    "tags": "back biceps lats traps pulling rowing straight-arm pulldown",
    "tip": "Prioritize control, full range where safe, and breathe with the pattern.",
    "thumbUrl": "https://i.ytimg.com/vi/sY9T_dHDxNM/hqdefault.jpg",
    "videoLabel": "YouTube (privacy-enhanced embed)",
    "youtubeId": "sY9T_dHDxNM"
  },
  {
    "id": "ex065",
    "title": "Chest-supported row",
    "cat": "upper_pull",
    "tags": "back biceps lats traps pulling rowing chest-supported row",
    "tip": "Prioritize control, full range where safe, and breathe with the pattern.",
    "thumbUrl": "https://i.ytimg.com/vi/FWJR5Ve8bnQ/hqdefault.jpg",
    "videoLabel": "YouTube (privacy-enhanced embed)",
    "youtubeId": "FWJR5Ve8bnQ"
  },
  {
    "id": "ex066",
    "title": "Cable row",
    "cat": "upper_pull",
    "tags": "back biceps lats traps pulling rowing cable row",
    "tip": "Prioritize control, full range where safe, and breathe with the pattern.",
    "thumbUrl": "https://i.ytimg.com/vi/roCP6wCXPqo/hqdefault.jpg",
    "videoLabel": "YouTube (privacy-enhanced embed)",
    "youtubeId": "roCP6wCXPqo"
  },
  {
    "id": "ex067",
    "title": "Seated cable row",
    "cat": "upper_pull",
    "tags": "back biceps lats traps pulling rowing seated cable row",
    "tip": "Prioritize control, full range where safe, and breathe with the pattern.",
    "thumbUrl": "https://i.ytimg.com/vi/roCP6wCXPqo/hqdefault.jpg",
    "videoLabel": "YouTube (privacy-enhanced embed)",
    "youtubeId": "roCP6wCXPqo"
  },
  {
    "id": "ex068",
    "title": "T-bar row",
    "cat": "upper_pull",
    "tags": "back biceps lats traps pulling rowing t-bar row",
    "tip": "Prioritize control, full range where safe, and breathe with the pattern.",
    "thumbUrl": "https://i.ytimg.com/vi/FWJR5Ve8bnQ/hqdefault.jpg",
    "videoLabel": "YouTube (privacy-enhanced embed)",
    "youtubeId": "FWJR5Ve8bnQ"
  },
  {
    "id": "ex069",
    "title": "Pendlay row",
    "cat": "upper_pull",
    "tags": "back biceps lats traps pulling rowing pendlay row",
    "tip": "Prioritize control, full range where safe, and breathe with the pattern.",
    "thumbUrl": "https://i.ytimg.com/vi/FWJR5Ve8bnQ/hqdefault.jpg",
    "videoLabel": "YouTube (privacy-enhanced embed)",
    "youtubeId": "FWJR5Ve8bnQ"
  },
  {
    "id": "ex070",
    "title": "Single-arm dumbbell row",
    "cat": "upper_pull",
    "tags": "back biceps lats traps pulling rowing single-arm dumbbell row",
    "tip": "Prioritize control, full range where safe, and breathe with the pattern.",
    "thumbUrl": "https://i.ytimg.com/vi/FWJR5Ve8bnQ/hqdefault.jpg",
    "videoLabel": "YouTube (privacy-enhanced embed)",
    "youtubeId": "FWJR5Ve8bnQ"
  },
  {
    "id": "ex071",
    "title": "Meadows row",
    "cat": "upper_pull",
    "tags": "back biceps lats traps pulling rowing meadows row",
    "tip": "Prioritize control, full range where safe, and breathe with the pattern.",
    "thumbUrl": "https://i.ytimg.com/vi/FWJR5Ve8bnQ/hqdefault.jpg",
    "videoLabel": "YouTube (privacy-enhanced embed)",
    "youtubeId": "FWJR5Ve8bnQ"
  },
  {
    "id": "ex072",
    "title": "Face pull",
    "cat": "upper_pull",
    "tags": "back biceps lats traps pulling rowing face pull",
    "tip": "Prioritize control, full range where safe, and breathe with the pattern.",
    "thumbUrl": "https://i.ytimg.com/vi/HSoHeSjvId4/hqdefault.jpg",
    "videoLabel": "YouTube (privacy-enhanced embed)",
    "youtubeId": "HSoHeSjvId4"
  },
  {
    "id": "ex073",
    "title": "Rear delt fly",
    "cat": "upper_pull",
    "tags": "back biceps lats traps pulling rowing rear delt fly",
    "tip": "Prioritize control, full range where safe, and breathe with the pattern.",
    "thumbUrl": "https://i.ytimg.com/vi/3VcKaXpzqRo/hqdefault.jpg",
    "videoLabel": "YouTube (privacy-enhanced embed)",
    "youtubeId": "3VcKaXpzqRo"
  },
  {
    "id": "ex074",
    "title": "Cable lateral raise",
    "cat": "upper_push",
    "tags": "chest shoulders triceps push pressing cable lateral raise",
    "tip": "Prioritize control, full range where safe, and breathe with the pattern.",
    "thumbUrl": "https://i.ytimg.com/vi/3VcKaXpzqRo/hqdefault.jpg",
    "videoLabel": "YouTube (privacy-enhanced embed)",
    "youtubeId": "3VcKaXpzqRo"
  },
  {
    "id": "ex075",
    "title": "Dumbbell lateral raise",
    "cat": "upper_push",
    "tags": "chest shoulders triceps push pressing dumbbell lateral raise",
    "tip": "Prioritize control, full range where safe, and breathe with the pattern.",
    "thumbUrl": "https://i.ytimg.com/vi/3VcKaXpzqRo/hqdefault.jpg",
    "videoLabel": "YouTube (privacy-enhanced embed)",
    "youtubeId": "3VcKaXpzqRo"
  },
  {
    "id": "ex076",
    "title": "Front raise",
    "cat": "upper_push",
    "tags": "chest shoulders triceps push pressing front raise",
    "tip": "Prioritize control, full range where safe, and breathe with the pattern.",
    "thumbUrl": "https://i.ytimg.com/vi/3VcKaXpzqRo/hqdefault.jpg",
    "videoLabel": "YouTube (privacy-enhanced embed)",
    "youtubeId": "3VcKaXpzqRo"
  },
  {
    "id": "ex077",
    "title": "Upright row",
    "cat": "upper_push",
    "tags": "chest shoulders triceps push pressing upright row",
    "tip": "Prioritize control, full range where safe, and breathe with the pattern.",
    "thumbUrl": "https://i.ytimg.com/vi/n6RjOx7UGV4/hqdefault.jpg",
    "videoLabel": "YouTube (privacy-enhanced embed)",
    "youtubeId": "n6RjOx7UGV4"
  },
  {
    "id": "ex078",
    "title": "Shrug",
    "cat": "arms",
    "tags": "biceps triceps forearms isolation shrug",
    "tip": "Prioritize control, full range where safe, and breathe with the pattern.",
    "thumbUrl": "https://i.ytimg.com/vi/n6RjOx7UGV4/hqdefault.jpg",
    "videoLabel": "YouTube (privacy-enhanced embed)",
    "youtubeId": "n6RjOx7UGV4"
  },
  {
    "id": "ex079",
    "title": "Barbell curl",
    "cat": "arms",
    "tags": "biceps triceps forearms isolation barbell curl",
    "tip": "Prioritize control, full range where safe, and breathe with the pattern.",
    "thumbUrl": "https://i.ytimg.com/vi/vB5OhOL872M/hqdefault.jpg",
    "videoLabel": "YouTube (privacy-enhanced embed)",
    "youtubeId": "vB5OhOL872M"
  },
  {
    "id": "ex080",
    "title": "Dumbbell curl",
    "cat": "arms",
    "tags": "biceps triceps forearms isolation dumbbell curl",
    "tip": "Prioritize control, full range where safe, and breathe with the pattern.",
    "thumbUrl": "https://i.ytimg.com/vi/vB5OhOL872M/hqdefault.jpg",
    "videoLabel": "YouTube (privacy-enhanced embed)",
    "youtubeId": "vB5OhOL872M"
  },
  {
    "id": "ex081",
    "title": "Hammer curl",
    "cat": "arms",
    "tags": "biceps triceps forearms isolation hammer curl",
    "tip": "Prioritize control, full range where safe, and breathe with the pattern.",
    "thumbUrl": "https://i.ytimg.com/vi/vB5OhOL872M/hqdefault.jpg",
    "videoLabel": "YouTube (privacy-enhanced embed)",
    "youtubeId": "vB5OhOL872M"
  },
  {
    "id": "ex082",
    "title": "Preacher curl",
    "cat": "arms",
    "tags": "biceps triceps forearms isolation preacher curl",
    "tip": "Prioritize control, full range where safe, and breathe with the pattern.",
    "thumbUrl": "https://i.ytimg.com/vi/vB5OhOL872M/hqdefault.jpg",
    "videoLabel": "YouTube (privacy-enhanced embed)",
    "youtubeId": "vB5OhOL872M"
  },
  {
    "id": "ex083",
    "title": "Cable curl",
    "cat": "arms",
    "tags": "biceps triceps forearms isolation cable curl",
    "tip": "Prioritize control, full range where safe, and breathe with the pattern.",
    "thumbUrl": "https://i.ytimg.com/vi/vB5OhOL872M/hqdefault.jpg",
    "videoLabel": "YouTube (privacy-enhanced embed)",
    "youtubeId": "vB5OhOL872M"
  },
  {
    "id": "ex084",
    "title": "Skull crusher",
    "cat": "arms",
    "tags": "biceps triceps forearms isolation skull crusher",
    "tip": "Prioritize control, full range where safe, and breathe with the pattern.",
    "thumbUrl": "https://i.ytimg.com/vi/d_KZxkYJ0VQ/hqdefault.jpg",
    "videoLabel": "YouTube (privacy-enhanced embed)",
    "youtubeId": "d_KZxkYJ0VQ"
  },
  {
    "id": "ex085",
    "title": "Overhead tricep extension",
    "cat": "arms",
    "tags": "biceps triceps forearms isolation overhead tricep extension",
    "tip": "Prioritize control, full range where safe, and breathe with the pattern.",
    "thumbUrl": "https://i.ytimg.com/vi/nRiJVZDpdL0/hqdefault.jpg",
    "videoLabel": "YouTube (privacy-enhanced embed)",
    "youtubeId": "nRiJVZDpdL0"
  },
  {
    "id": "ex086",
    "title": "Tricep pushdown",
    "cat": "arms",
    "tags": "biceps triceps forearms isolation tricep pushdown",
    "tip": "Prioritize control, full range where safe, and breathe with the pattern.",
    "thumbUrl": "https://i.ytimg.com/vi/nRiJVZDpdL0/hqdefault.jpg",
    "videoLabel": "YouTube (privacy-enhanced embed)",
    "youtubeId": "nRiJVZDpdL0"
  },
  {
    "id": "ex087",
    "title": "Rope pushdown",
    "cat": "arms",
    "tags": "biceps triceps forearms isolation rope pushdown",
    "tip": "Prioritize control, full range where safe, and breathe with the pattern.",
    "thumbUrl": "https://i.ytimg.com/vi/nRiJVZDpdL0/hqdefault.jpg",
    "videoLabel": "YouTube (privacy-enhanced embed)",
    "youtubeId": "nRiJVZDpdL0"
  },
  {
    "id": "ex088",
    "title": "Single-arm pushdown",
    "cat": "arms",
    "tags": "biceps triceps forearms isolation single-arm pushdown",
    "tip": "Prioritize control, full range where safe, and breathe with the pattern.",
    "thumbUrl": "https://i.ytimg.com/vi/nRiJVZDpdL0/hqdefault.jpg",
    "videoLabel": "YouTube (privacy-enhanced embed)",
    "youtubeId": "nRiJVZDpdL0"
  },
  {
    "id": "ex089",
    "title": "Cable kickback",
    "cat": "arms",
    "tags": "biceps triceps forearms isolation cable kickback",
    "tip": "Prioritize control, full range where safe, and breathe with the pattern.",
    "thumbUrl": "https://i.ytimg.com/vi/nRiJVZDpdL0/hqdefault.jpg",
    "videoLabel": "YouTube (privacy-enhanced embed)",
    "youtubeId": "nRiJVZDpdL0"
  },
  {
    "id": "ex090",
    "title": "Plank",
    "cat": "core",
    "tags": "abs obliques trunk anti-rotation plank",
    "tip": "Prioritize control, full range where safe, and breathe with the pattern.",
    "thumbUrl": "https://i.ytimg.com/vi/pSHjTRCQ8Iw/hqdefault.jpg",
    "videoLabel": "YouTube (privacy-enhanced embed)",
    "youtubeId": "pSHjTRCQ8Iw"
  },
  {
    "id": "ex091",
    "title": "Side plank",
    "cat": "core",
    "tags": "abs obliques trunk anti-rotation side plank",
    "tip": "Prioritize control, full range where safe, and breathe with the pattern.",
    "thumbUrl": "https://i.ytimg.com/vi/pSHjTRCQ8Iw/hqdefault.jpg",
    "videoLabel": "YouTube (privacy-enhanced embed)",
    "youtubeId": "pSHjTRCQ8Iw"
  },
  {
    "id": "ex092",
    "title": "Dead bug",
    "cat": "core",
    "tags": "abs obliques trunk anti-rotation dead bug",
    "tip": "Prioritize control, full range where safe, and breathe with the pattern.",
    "thumbUrl": "https://i.ytimg.com/vi/DJQim2lqc8k/hqdefault.jpg",
    "videoLabel": "YouTube (privacy-enhanced embed)",
    "youtubeId": "DJQim2lqc8k"
  },
  {
    "id": "ex093",
    "title": "Bird dog",
    "cat": "core",
    "tags": "abs obliques trunk anti-rotation bird dog",
    "tip": "Prioritize control, full range where safe, and breathe with the pattern.",
    "thumbUrl": "https://i.ytimg.com/vi/DJQim2lqc8k/hqdefault.jpg",
    "videoLabel": "YouTube (privacy-enhanced embed)",
    "youtubeId": "DJQim2lqc8k"
  },
  {
    "id": "ex094",
    "title": "Ab wheel rollout",
    "cat": "core",
    "tags": "abs obliques trunk anti-rotation ab wheel rollout",
    "tip": "Prioritize control, full range where safe, and breathe with the pattern.",
    "thumbUrl": "https://i.ytimg.com/vi/ghDQdDjw214/hqdefault.jpg",
    "videoLabel": "YouTube (privacy-enhanced embed)",
    "youtubeId": "ghDQdDjw214"
  },
  {
    "id": "ex095",
    "title": "Hanging leg raise",
    "cat": "core",
    "tags": "abs obliques trunk anti-rotation hanging leg raise",
    "tip": "Prioritize control, full range where safe, and breathe with the pattern.",
    "thumbUrl": "https://i.ytimg.com/vi/ghDQdDjw214/hqdefault.jpg",
    "videoLabel": "YouTube (privacy-enhanced embed)",
    "youtubeId": "ghDQdDjw214"
  },
  {
    "id": "ex096",
    "title": "Knee raise",
    "cat": "core",
    "tags": "abs obliques trunk anti-rotation knee raise",
    "tip": "Prioritize control, full range where safe, and breathe with the pattern.",
    "thumbUrl": "https://i.ytimg.com/vi/ghDQdDjw214/hqdefault.jpg",
    "videoLabel": "YouTube (privacy-enhanced embed)",
    "youtubeId": "ghDQdDjw214"
  },
  {
    "id": "ex097",
    "title": "Russian twist",
    "cat": "core",
    "tags": "abs obliques trunk anti-rotation russian twist",
    "tip": "Prioritize control, full range where safe, and breathe with the pattern.",
    "thumbUrl": "https://i.ytimg.com/vi/nmwgirgXLYM/hqdefault.jpg",
    "videoLabel": "YouTube (privacy-enhanced embed)",
    "youtubeId": "nmwgirgXLYM"
  },
  {
    "id": "ex098",
    "title": "Cable woodchop",
    "cat": "core",
    "tags": "abs obliques trunk anti-rotation cable woodchop",
    "tip": "Prioritize control, full range where safe, and breathe with the pattern.",
    "thumbUrl": "https://i.ytimg.com/vi/nmwgirgXLYM/hqdefault.jpg",
    "videoLabel": "YouTube (privacy-enhanced embed)",
    "youtubeId": "nmwgirgXLYM"
  },
  {
    "id": "ex099",
    "title": "Pallof press",
    "cat": "core",
    "tags": "abs obliques trunk anti-rotation pallof press",
    "tip": "Prioritize control, full range where safe, and breathe with the pattern.",
    "thumbUrl": "https://i.ytimg.com/vi/nmwgirgXLYM/hqdefault.jpg",
    "videoLabel": "YouTube (privacy-enhanced embed)",
    "youtubeId": "nmwgirgXLYM"
  },
  {
    "id": "ex100",
    "title": "Mountain climber",
    "cat": "cardio",
    "tags": "conditioning hiit heart rate endurance mountain climber",
    "tip": "Prioritize control, full range where safe, and breathe with the pattern.",
    "thumbUrl": "https://i.ytimg.com/vi/dZgVxmfkXuM/hqdefault.jpg",
    "videoLabel": "YouTube (privacy-enhanced embed)",
    "youtubeId": "dZgVxmfkXuM"
  },
  {
    "id": "ex101",
    "title": "Burpee",
    "cat": "cardio",
    "tags": "conditioning hiit heart rate endurance burpee",
    "tip": "Prioritize control, full range where safe, and breathe with the pattern.",
    "thumbUrl": "https://i.ytimg.com/vi/dZgVxmfkXuM/hqdefault.jpg",
    "videoLabel": "YouTube (privacy-enhanced embed)",
    "youtubeId": "dZgVxmfkXuM"
  },
  {
    "id": "ex102",
    "title": "Jump squat",
    "cat": "cardio",
    "tags": "conditioning hiit heart rate endurance jump squat",
    "tip": "Prioritize control, full range where safe, and breathe with the pattern.",
    "thumbUrl": "https://i.ytimg.com/vi/xqvCmoiphqM/hqdefault.jpg",
    "videoLabel": "YouTube (privacy-enhanced embed)",
    "youtubeId": "xqvCmoiphqM"
  },
  {
    "id": "ex103",
    "title": "Box jump",
    "cat": "cardio",
    "tags": "conditioning hiit heart rate endurance box jump",
    "tip": "Prioritize control, full range where safe, and breathe with the pattern.",
    "thumbUrl": "https://i.ytimg.com/vi/NBY9-kTuohk/hqdefault.jpg",
    "videoLabel": "YouTube (privacy-enhanced embed)",
    "youtubeId": "NBY9-kTuohk"
  },
  {
    "id": "ex104",
    "title": "Kettlebell swing",
    "cat": "cardio",
    "tags": "conditioning hiit heart rate endurance kettlebell swing",
    "tip": "Prioritize control, full range where safe, and breathe with the pattern.",
    "thumbUrl": "https://i.ytimg.com/vi/1cVT3ee9mgU/hqdefault.jpg",
    "videoLabel": "YouTube (privacy-enhanced embed)",
    "youtubeId": "1cVT3ee9mgU"
  },
  {
    "id": "ex105",
    "title": "Battle ropes",
    "cat": "cardio",
    "tags": "conditioning hiit heart rate endurance battle ropes",
    "tip": "Prioritize control, full range where safe, and breathe with the pattern.",
    "thumbUrl": "https://i.ytimg.com/vi/pI65w6ebY9g/hqdefault.jpg",
    "videoLabel": "YouTube (privacy-enhanced embed)",
    "youtubeId": "pI65w6ebY9g"
  }
]